[{"id":1,"name":"Boyer, Runte and Bergnaum","address":"14th Floor","rate":4},
{"id":2,"name":"Bogan Group","address":"PO Box 13080","rate":4},
{"id":3,"name":"Marquardt, Goodwin and Stiedemann","address":"Room 1596","rate":5},
{"id":4,"name":"Morissette-Waelchi","address":"Suite 40","rate":2},
{"id":5,"name":"Haag-Yundt","address":"Room 1579","rate":3},
{"id":6,"name":"Lynch-Bailey","address":"20th Floor","rate":5},
{"id":7,"name":"Carroll and Sons","address":"12th Floor","rate":4},
{"id":8,"name":"Powlowski LLC","address":"PO Box 97205","rate":3},
{"id":9,"name":"Hoeger-Schuster","address":"19th Floor","rate":2},
{"id":10,"name":"White-Parker","address":"10th Floor","rate":3},
{"id":11,"name":"Kub-Wiegand","address":"Suite 37","rate":3},
{"id":12,"name":"Steuber, Robel and McDermott","address":"Suite 22","rate":5},
{"id":13,"name":"Hessel LLC","address":"Apt 384","rate":4},
{"id":14,"name":"Klein Group","address":"Room 1989","rate":5},
{"id":15,"name":"Bechtelar-Rogahn","address":"19th Floor","rate":4},
{"id":16,"name":"Kub LLC","address":"Suite 60","rate":5},
{"id":17,"name":"Altenwerth-Barrows","address":"Suite 94","rate":2},
{"id":18,"name":"VonRueden-Labadie","address":"Apt 1136","rate":2},
{"id":19,"name":"Swift-Lueilwitz","address":"9th Floor","rate":2},
{"id":20,"name":"Okuneva-Glover","address":"Suite 57","rate":3},
{"id":21,"name":"Ankunding, Hammes and Wolff","address":"7th Floor","rate":2},
{"id":22,"name":"Cruickshank LLC","address":"1st Floor","rate":3},
{"id":23,"name":"Ernser, Lakin and Witting","address":"PO Box 40133","rate":2},
{"id":24,"name":"Runolfsson-Bode","address":"Suite 90","rate":3},
{"id":25,"name":"Kerluke, Trantow and Strosin","address":"4th Floor","rate":5},
{"id":26,"name":"Schultz-Kunze","address":"Suite 59","rate":5},
{"id":27,"name":"Kuhic, Moen and Abbott","address":"Suite 49","rate":3},
{"id":28,"name":"Kassulke, Bechtelar and Kiehn","address":"PO Box 1413","rate":5},
{"id":29,"name":"Torp LLC","address":"Room 710","rate":5},
{"id":30,"name":"Bartell Group","address":"Suite 4","rate":2},
{"id":31,"name":"Kohler-Kulas","address":"Suite 76","rate":5},
{"id":32,"name":"Anderson-Paucek","address":"Room 625","rate":3},
{"id":33,"name":"Herzog Group","address":"Suite 9","rate":3},
{"id":34,"name":"O'Keefe-Wolff","address":"Room 1209","rate":3},
{"id":35,"name":"Pollich-Beier","address":"Suite 57","rate":3},
{"id":36,"name":"Berge, Effertz and Reinger","address":"Suite 83","rate":2},
{"id":37,"name":"Jaskolski-Walter","address":"Apt 927","rate":5},
{"id":38,"name":"Roob-Metz","address":"Room 1673","rate":3},
{"id":39,"name":"Koepp LLC","address":"5th Floor","rate":5},
{"id":40,"name":"Langworth, Parker and Toy","address":"Suite 9","rate":4},
{"id":41,"name":"Roberts Group","address":"11th Floor","rate":3},
{"id":42,"name":"Jast, Hansen and Ziemann","address":"PO Box 99949","rate":5},
{"id":43,"name":"Schoen, Dicki and Reilly","address":"17th Floor","rate":4},
{"id":44,"name":"Ryan, Vandervort and Conn","address":"14th Floor","rate":4},
{"id":45,"name":"Towne, Stoltenberg and Hartmann","address":"PO Box 71019","rate":5},
{"id":46,"name":"Conn, Renner and Streich","address":"Room 1939","rate":5},
{"id":47,"name":"Schultz-Abernathy","address":"Room 415","rate":2},
{"id":48,"name":"Mosciski Group","address":"Apt 301","rate":2},
{"id":49,"name":"Hermiston, Altenwerth and Littel","address":"Apt 1014","rate":4},
{"id":50,"name":"Champlin Inc","address":"Room 458","rate":4},
{"id":51,"name":"Bergstrom and Sons","address":"Apt 272","rate":4},
{"id":52,"name":"Collier, Feeney and Morissette","address":"Suite 11","rate":5},
{"id":53,"name":"VonRueden Inc","address":"Apt 893","rate":3},
{"id":54,"name":"Altenwerth-Hane","address":"Suite 78","rate":4},
{"id":55,"name":"McGlynn LLC","address":"PO Box 28651","rate":3},
{"id":56,"name":"Leffler Inc","address":"7th Floor","rate":3},
{"id":57,"name":"Leannon-Auer","address":"Suite 41","rate":2},
{"id":58,"name":"Reichert, Emard and McClure","address":"Room 1644","rate":4},
{"id":59,"name":"Denesik, Rolfson and Hand","address":"Room 1642","rate":3},
{"id":60,"name":"Pfeffer, Senger and Johnston","address":"Room 184","rate":3},
{"id":61,"name":"Cartwright, Little and Stroman","address":"PO Box 8031","rate":3},
{"id":62,"name":"Runte and Sons","address":"5th Floor","rate":4},
{"id":63,"name":"Russel, Kshlerin and Hodkiewicz","address":"Suite 62","rate":4},
{"id":64,"name":"Ritchie, Considine and Borer","address":"Suite 25","rate":3},
{"id":65,"name":"Buckridge, Leuschke and Sporer","address":"PO Box 79685","rate":2},
{"id":66,"name":"Jakubowski-Pacocha","address":"PO Box 28672","rate":3},
{"id":67,"name":"Turcotte and Sons","address":"Room 240","rate":5},
{"id":68,"name":"Will Inc","address":"PO Box 22003","rate":3},
{"id":69,"name":"Anderson-Smitham","address":"19th Floor","rate":5},
{"id":70,"name":"Schowalter and Sons","address":"Suite 57","rate":2},
{"id":71,"name":"Jenkins LLC","address":"19th Floor","rate":5},
{"id":72,"name":"Parker, Willms and Murray","address":"7th Floor","rate":4},
{"id":73,"name":"Kertzmann, Dare and Bahringer","address":"PO Box 98806","rate":3},
{"id":74,"name":"Wisozk and Sons","address":"Suite 47","rate":3},
{"id":75,"name":"Lehner-Nienow","address":"Room 383","rate":5},
{"id":76,"name":"Sporer, Treutel and Quigley","address":"PO Box 87311","rate":2},
{"id":77,"name":"Nitzsche, Walsh and Daniel","address":"Apt 1444","rate":3},
{"id":78,"name":"Labadie-Marvin","address":"Apt 1257","rate":5},
{"id":79,"name":"Larkin, Stark and Collier","address":"14th Floor","rate":3},
{"id":80,"name":"Deckow, Littel and DuBuque","address":"Room 623","rate":2},
{"id":81,"name":"Marks Group","address":"Apt 149","rate":2},
{"id":82,"name":"Lowe Group","address":"9th Floor","rate":4},
{"id":83,"name":"Wolff-Moen","address":"Apt 1322","rate":2},
{"id":84,"name":"Batz, Prosacco and McDermott","address":"Room 1920","rate":4},
{"id":85,"name":"Hoeger-Schmeler","address":"15th Floor","rate":5},
{"id":86,"name":"Bernhard Group","address":"3rd Floor","rate":3},
{"id":87,"name":"Schiller-Daugherty","address":"Room 1803","rate":5},
{"id":88,"name":"Nienow, Waters and Fisher","address":"Room 1807","rate":5},
{"id":89,"name":"Pagac, Kshlerin and Bechtelar","address":"11th Floor","rate":5},
{"id":90,"name":"Runte-Auer","address":"Room 1645","rate":3},
{"id":91,"name":"Schumm, Ryan and Dooley","address":"Suite 29","rate":3},
{"id":92,"name":"Wiegand, Bergnaum and Murazik","address":"Room 1421","rate":5},
{"id":93,"name":"McCullough-Koelpin","address":"Room 1339","rate":2},
{"id":94,"name":"Ziemann LLC","address":"Apt 1886","rate":3},
{"id":95,"name":"Langosh Inc","address":"PO Box 84230","rate":4},
{"id":96,"name":"Cole-Nader","address":"Room 54","rate":5},
{"id":97,"name":"Balistreri and Sons","address":"Room 771","rate":2},
{"id":98,"name":"Bogisich Inc","address":"Room 782","rate":3},
{"id":99,"name":"Rice, Bergstrom and Johnston","address":"2nd Floor","rate":5},
{"id":100,"name":"Purdy Group","address":"PO Box 8154","rate":3}]